LICENSE.txt
README.txt
setup.py
luhn_abstract/__init__.py
luhn_abstract/luhn_abstract.py
luhn_abstract.egg-info/PKG-INFO
luhn_abstract.egg-info/SOURCES.txt
luhn_abstract.egg-info/dependency_links.txt
luhn_abstract.egg-info/top_level.txt