Metadata-Version: 2.1
Name: luhn-abstract
Version: 0.1.1
Summary: A library for automatically generating an abstract from a document using unsupervised techniques.
Home-page: https://github.com/JIVJGFJZKF/luhn
Author: 
Author-email: 
Classifier: Programming Language :: Python :: 3
Classifier: License :: OSI Approved :: GNU General Public License v3 or later (GPLv3+)
Classifier: Operating System :: OS Independent
Requires-Python: >=3.6
License-File: LICENSE.txt
